conflict_rpa/__init__.py
conflict_rpa/config.py
conflict_rpa/content_rpa.py
conflict_rpa/correcting_framework.py
conflict_rpa/environment_setting.py
conflict_rpa/file_operation.py
conflict_rpa/get_running_env.py
conflict_rpa/link_rpa.py
conflict_rpa/rpa.py
conflict_rpa/utils.py
conflict_rpa-0.1.0.dist-info/METADATA
conflict_rpa-0.1.0.dist-info/WHEEL
conflict_rpa-0.1.0.dist-info/entry_points.txt
conflict_rpa-0.1.0.dist-info/top_level.txt
conflict_rpa-0.1.0.dist-info/RECORD
