Metadata-Version: 2.1
Name: conflict_rpa
Version: 0.1.0
Summary: A tool to rpa in your shell
Author: FanYangli
Author-email: yong.feng@centurygame.com
Requires-Dist: openai >=1.28.1
Requires-Dist: requests >=2.22.0
